gai/llm/client/__init__.py
gai/llm/client/async_chat_client.py
gai/llm/client/chat_client.py
gai/llm/lib/__init__.py
gai/llm/lib/dtos.py
gai/llm/lib/generators_utils.py
gai/llm/lib/llm_retry_policy.py
gai/llm/openai/__init__.py
gai/llm/openai/async_patch.py
gai/llm/openai/attach_extractor.py
gai/llm/openai/json_schemas.py
gai/llm/openai/patch copy.py
gai/llm/openai/patch.py
gai/llm/openai/patch_common.py
gai/llm/openai/types.py
gai/llm/openai/response/output_chunk_builder_base.py
gai/llm/openai/response/output_message_builder_base.py
gai/llm/openai/response/anthropic/completions_factory.py
gai/llm/openai/response/anthropic/output_chunk_builder copy.py
gai/llm/openai/response/anthropic/output_chunk_builder.py
gai/llm/openai/response/anthropic/output_message_builder copy.py
gai/llm/openai/response/anthropic/output_message_builder.py
gai/llm/openai/response/ollama/__init__.py
gai/llm/openai/response/ollama/completions_factory.py
gai/llm/openai/response/ollama/output_chunk_builder.py
gai/llm/openai/response/ollama/output_message_builder.py
gai_llm-0.1.4.dist-info/METADATA
gai_llm-0.1.4.dist-info/WHEEL
gai_llm-0.1.4.dist-info/licenses/LICENSE
gai_llm-0.1.4.dist-info/RECORD
