Metadata-Version: 2.4
Name: gai-llm
Version: 0.1.4
Author-email: kakkoii1337 <kakkoii1337@gmail.com>
License: MIT License
License-File: LICENSE
Requires-Python: >=3.10
Requires-Dist: anthropic>=0.52.1
Requires-Dist: fastapi>=0.115.12
Requires-Dist: gai-lib
Requires-Dist: jsonschema==4.24.0
Requires-Dist: ollama==0.4.6
Provides-Extra: dev
Requires-Dist: gai-lib[dev]; extra == 'dev'
